incli/__init__.py
incli/incli.py
incli/sfapi/CPQ.py
incli/sfapi/CPQAppHandler.py
incli/sfapi/CPQUtil.py
incli/sfapi/DR_IP.py
incli/sfapi/DicPath.py
incli/sfapi/OM.py
incli/sfapi/Sobjects.py
incli/sfapi/VlocityErrorLog.py
incli/sfapi/VlocityTrackingEntry.py
incli/sfapi/__init__.py
incli/sfapi/account.py
incli/sfapi/cartUtils.py
incli/sfapi/cometd.py
incli/sfapi/debugLogs.py
incli/sfapi/debugLogsPrint.py
incli/sfapi/digitalCommerce.py
incli/sfapi/digitalCommerceUtil.py
incli/sfapi/elementParser.py
incli/sfapi/file.py
incli/sfapi/file_csv.py
incli/sfapi/houseKeep.py
incli/sfapi/invocableactions.py
incli/sfapi/ip_attachments.py
incli/sfapi/jsonFile.py
incli/sfapi/objectUtil.py
incli/sfapi/parse.py
incli/sfapi/priceBook.py
incli/sfapi/product.py
incli/sfapi/query.py
incli/sfapi/restClient.py
incli/sfapi/thread.py
incli/sfapi/timeStats.py
incli/sfapi/tooling.py
incli/sfapi/traceFlag.py
incli/sfapi/utils.py
incli-0.2.113.dist-info/licenses/LICENSE.txt
incli-0.2.113.dist-info/METADATA
incli-0.2.113.dist-info/WHEEL
incli-0.2.113.dist-info/entry_points.txt
incli-0.2.113.dist-info/top_level.txt
incli-0.2.113.dist-info/RECORD
