Metadata-Version: 2.4
Name: incli
Version: 0.2.113
Summary: CLI utilities for ...
Author: Unaior
Author-email: unaior@gmail.com
License-Expression: MIT
Project-URL: repository, https://github.com/unaior/InCli
License-File: LICENSE.txt
Requires-Dist: simplejson
Requires-Dist: requests<2.28.2,>=2.28.1
Requires-Dist: urllib3<1.26.16,>=1.26.15
Requires-Dist: colorama
Requires-Dist: ansi2html
Dynamic: license-file
